Metadata-Version: 2.1
Name: movement-detector
Version: 0.2.4
Summary: Detect movement in videos.
Home-page: https://github.com/petioptrv/movement_detector
Author: Petio Petrov
License: MIT License
Keywords: movement detection freezing behavioural behaviour behavioralbehavior research
Platform: UNKNOWN
Classifier: Development Status :: 3 - Alpha
Classifier: Intended Audience :: Science/Research
Classifier: Programming Language :: Python :: 3.6
Classifier: Programming Language :: Python :: 3.7
Classifier: Programming Language :: Python :: 3.8
Provides-Extra: dev
Provides-Extra: interface
